odoo/addons/project_task_project_required/README.rst
odoo/addons/project_task_project_required/__init__.py
odoo/addons/project_task_project_required/__manifest__.py
odoo/addons/project_task_project_required/demo/res_company.xml
odoo/addons/project_task_project_required/i18n/es.po
odoo/addons/project_task_project_required/i18n/it.po
odoo/addons/project_task_project_required/i18n/project_task_project_required.pot
odoo/addons/project_task_project_required/i18n/pt_BR.po
odoo/addons/project_task_project_required/models/__init__.py
odoo/addons/project_task_project_required/models/project_task.py
odoo/addons/project_task_project_required/models/res_company.py
odoo/addons/project_task_project_required/models/res_config_settings.py
odoo/addons/project_task_project_required/readme/CONFIGURE.rst
odoo/addons/project_task_project_required/readme/CONTRIBUTORS.rst
odoo/addons/project_task_project_required/readme/DESCRIPTION.rst
odoo/addons/project_task_project_required/static/description/icon.png
odoo/addons/project_task_project_required/static/description/index.html
odoo/addons/project_task_project_required/tests/__init__.py
odoo/addons/project_task_project_required/tests/test_project_task_project_required.py
odoo/addons/project_task_project_required/views/project_task.xml
odoo/addons/project_task_project_required/views/res_config_settings_views.xml
odoo_addon_project_task_project_required-16.0.1.0.0.4.dist-info/METADATA
odoo_addon_project_task_project_required-16.0.1.0.0.4.dist-info/WHEEL
odoo_addon_project_task_project_required-16.0.1.0.0.4.dist-info/top_level.txt
odoo_addon_project_task_project_required-16.0.1.0.0.4.dist-info/RECORD
